graph_trackintel/__init__.py
graph_trackintel/activity_graph.py
graph_trackintel/graph_utils.py
graph_trackintel/io.py
graph_trackintel/plotting.py
graph_trackintel/analysis/__init__.py
graph_trackintel/analysis/graph_features.py
tests/__init__.py
tests/test_activity_graph.py
tests/test_activity_graph2.py
tests/test_graph_features.py
tests/test_io.py
graph_trackintel-0.0.7.dist-info/LICENSE
graph_trackintel-0.0.7.dist-info/METADATA
graph_trackintel-0.0.7.dist-info/WHEEL
graph_trackintel-0.0.7.dist-info/top_level.txt
graph_trackintel-0.0.7.dist-info/RECORD
