Metadata-Version: 2.1
Name: graph-trackintel
Version: 0.0.7
Summary: Tools for creating, processing and analyzing location graphs
Home-page: https://github.com/mie-lab/graph-trackintel
Author: MIE Lab
Author-email: nwiedemann@ethz.ch
License: MIT
Classifier: License :: OSI Approved :: MIT License
Classifier: Intended Audience :: Science/Research
Classifier: Programming Language :: Python :: 3.6
Classifier: Topic :: Software Development :: Libraries :: Python Modules
Requires-Python: >=3.6
License-File: LICENSE
Requires-Dist: numpy
Requires-Dist: scipy
Requires-Dist: psycopg2
Requires-Dist: networkx
Requires-Dist: pyproj
Requires-Dist: matplotlib
Requires-Dist: trackintel
Requires-Dist: powerlaw
